{
  "order_id": "ORDER-TZNRS86S",
  "persona_id": "persona_027",
  "store_id": "amazon",
  "status": "delivered",
  "created_at": "2026-01-22T08:04:29",
  "shipped_at": "2026-01-23T08:04:29",
  "delivered_at": "2026-01-28T08:04:29",
  "shipping_address": "123 Jamaica Plain Rd, Boston, MA 02130",
  "items": [
    {
      "product_id": "B0TOYS0146",
      "name": "Celestron Celestron Telescope for Kids",
      "category": "Toys & Games",
      "quantity": 3,
      "price": 53.13,
      "subtotal": 159.39
    }
  ],
  "total": 159.39,
  "currency": "USD"
}