{
  "order_id": "ORDER-LHAK8TCX",
  "persona_id": "persona_027",
  "store_id": "amazon",
  "status": "delivered",
  "created_at": "2025-10-30T10:51:46",
  "shipped_at": "2025-10-31T10:51:46",
  "delivered_at": "2025-11-02T10:51:46",
  "shipping_address": "123 Jamaica Plain Rd, Boston, MA 02130",
  "items": [
    {
      "product_id": "B0TOYS0132",
      "name": "Wild Republic Wild Republic Tiger",
      "category": "Toys & Games",
      "quantity": 1,
      "price": 16.2,
      "subtotal": 16.2
    },
    {
      "product_id": "B0AMZN1214",
      "name": "Dynamax Standard Medicine Ball 14 lb",
      "category": "Sports & Outdoors",
      "quantity": 1,
      "price": 119.0,
      "subtotal": 119.0
    }
  ],
  "total": 135.2,
  "currency": "USD"
}