{
  "order_id": "WMT-KUQIRJDA",
  "persona_id": "persona_022",
  "store_id": "walmart",
  "status": "shipped",
  "created_at": "2025-12-10T02:12:37",
  "shipped_at": "2025-12-12T02:12:37",
  "delivered_at": "",
  "shipping_address": "444 Polish Hill St, Philadelphia, PA 19123",
  "items": [
    {
      "product_id": "WMT00001523",
      "name": "Van Ness Van Ness Automatic Feeder",
      "category": "Pets",
      "quantity": 2,
      "price": 24.88,
      "subtotal": 49.76
    },
    {
      "product_id": "WMT00001632",
      "name": "Fancy Feast Fancy Feast Medleys Collection",
      "category": "Pets",
      "quantity": 2,
      "price": 28.08,
      "subtotal": 56.16
    },
    {
      "product_id": "WMT00000578",
      "name": "Primal Kitchen Japanese Mayo",
      "category": "Grocery",
      "quantity": 3,
      "price": 4.63,
      "subtotal": 13.89
    },
    {
      "product_id": "WMT00001517",
      "name": "Armarkat Armarkat Classic Cat Tree",
      "category": "Pets",
      "quantity": 1,
      "price": 154.32,
      "subtotal": 154.32
    },
    {
      "product_id": "WMT00001428",
      "name": "Purina Purina ONE Indoor Advantage",
      "category": "Pets",
      "quantity": 1,
      "price": 27.26,
      "subtotal": 27.26
    }
  ],
  "total": 301.39,
  "currency": "USD"
}