{
  "order_id": "GRC000018",
  "persona_id": "persona_010",
  "store_id": "grocery",
  "status": "delivered",
  "created_at": "2025-10-13T18:23:06",
  "shipped_at": "",
  "delivered_at": "",
  "shipping_address": "321 French Quarter Ave, New Orleans, LA 70116",
  "items": [
    {
      "product_id": "prod_629",
      "name": "Golden Harvest Organic Lemonade",
      "category": "Beverages",
      "quantity": 3,
      "price": 5.68,
      "subtotal": 17.04
    },
    {
      "product_id": "GRO-1806",
      "name": "Organic Valley Eggs Large Dozen",
      "category": "Dairy",
      "quantity": 3,
      "price": 9.36,
      "subtotal": 28.08
    },
    {
      "product_id": "prod_261",
      "name": "Fresh Farms Pork Ribs",
      "category": "Meat & Seafood",
      "quantity": 2,
      "price": 28.94,
      "subtotal": 57.88
    },
    {
      "product_id": "prod_587",
      "name": "Heritage Foods Organic Frozen Lasagna",
      "category": "Frozen",
      "quantity": 3,
      "price": 14.65,
      "subtotal": 43.95
    },
    {
      "product_id": "prod_779",
      "name": "Premium Select Organic Cereal Rice Krispies",
      "category": "Breakfast",
      "quantity": 1,
      "price": 6.83,
      "subtotal": 6.83
    },
    {
      "product_id": "GRO-1022",
      "name": "Fresh Express Fresh Oregano",
      "category": "Produce",
      "quantity": 1,
      "price": 1.64,
      "subtotal": 1.64
    },
    {
      "product_id": "prod_500",
      "name": "Organic Choice Focaccia",
      "category": "Bakery",
      "quantity": 5,
      "price": 5.15,
      "subtotal": 25.75
    },
    {
      "product_id": "prod_865",
      "name": "Market Fresh Relish",
      "category": "Condiments & Spices",
      "quantity": 2,
      "price": 3.0,
      "subtotal": 6.0
    },
    {
      "product_id": "prod_844",
      "name": "Mountain Fresh Organic Bay Leaves",
      "category": "Condiments & Spices",
      "quantity": 2,
      "price": 7.12,
      "subtotal": 14.24
    },
    {
      "product_id": "GRO-1626",
      "name": "Organic Valley Bing Cherry",
      "category": "Produce",
      "quantity": 3,
      "price": 7.9,
      "subtotal": 23.7
    },
    {
      "product_id": "prod_029",
      "name": "Fresh Farms Apples",
      "category": "Produce",
      "quantity": 2,
      "price": 4.35,
      "subtotal": 8.7
    },
    {
      "product_id": "prod_063",
      "name": "Farm Fresh Peaches",
      "category": "Produce",
      "quantity": 2,
      "price": 9.05,
      "subtotal": 18.1
    }
  ],
  "total": 251.91,
  "currency": "USD"
}