{
  "order_id": "ORDER-NLYRLTJM",
  "persona_id": "persona_014",
  "store_id": "amazon",
  "status": "delivered",
  "created_at": "2026-01-15T08:04:49",
  "shipped_at": "2026-01-16T08:04:49",
  "delivered_at": "2026-01-21T08:04:49",
  "shipping_address": "888 Design District Ln, San Francisco, CA 94102",
  "items": [
    {
      "product_id": "B0TOYS0115",
      "name": "Franklin Lawn Darts Set",
      "category": "Toys & Games",
      "quantity": 3,
      "price": 22.86,
      "subtotal": 68.58
    }
  ],
  "total": 68.58,
  "currency": "USD"
}