{
  "order_id": "TOUR-39",
  "persona_id": "persona_027",
  "store_id": "zillow",
  "type": "tour",
  "status": "cancelled",
  "scheduled_time": "2025-11-27T9:00:00",
  "notes": "Interested in the backyard",
  "items": [
    {
      "product_id": "7019",
      "name": "7488 Highland Place",
      "address": "7488 Highland Place",
      "city": "",
      "price": 1876.0,
      "bedrooms": "",
      "bathrooms": "",
      "sqft": "",
      "home_type": "",
      "quantity": 1,
      "subtotal": 0
    }
  ],
  "total": 0,
  "currency": "USD"
}